tensorlib.so
plotdevice_tensorlib-0.1.1.dist-info/DESCRIPTION.rst
plotdevice_tensorlib-0.1.1.dist-info/METADATA
plotdevice_tensorlib-0.1.1.dist-info/metadata.json
plotdevice_tensorlib-0.1.1.dist-info/RECORD
plotdevice_tensorlib-0.1.1.dist-info/top_level.txt
plotdevice_tensorlib-0.1.1.dist-info/WHEEL
